statsd/__init__.py
statsd/client.py
statsd/tests.py
statsd/defaults/__init__.py
statsd/defaults/django.py
statsd/defaults/env.py
statsd_tags-3.2.1.post1.dist-info/DESCRIPTION.rst
statsd_tags-3.2.1.post1.dist-info/METADATA
statsd_tags-3.2.1.post1.dist-info/RECORD
statsd_tags-3.2.1.post1.dist-info/WHEEL
statsd_tags-3.2.1.post1.dist-info/metadata.json
statsd_tags-3.2.1.post1.dist-info/top_level.txt
